{
  "format": "viewtk-endomaze/v1",
  "map": "EndoMaze666",
  "space": "vtk-model-coordinates",
  "saved": "2026-07-06T15:19:48.359Z",
  "counts": {
    "RF": 24,
    "PFA": 93
  },
  "points": [
    {
      "id": 1,
      "group": "RF",
      "surface": "LA ENDO (CT).vtk",
      "comment": "",
      "x": -8.991178510745243,
      "y": -184.55457320625925,
      "z": -147.39174903440872
    },
    {
      "id": 2,
      "group": "RF",
      "surface": "LA ENDO (CT).vtk",
      "comment": "",
      "x": -11.927581890019496,
      "y": -187.4139322084773,
      "z": -151.89280541306533
    },
    {
      "id": 3,
      "group": "RF",
      "surface": "LA ENDO (CT).vtk",
      "comment": "",
      "x": -13.146779609873278,
      "y": -189.57706728476876,
      "z": -156.02133879411662
    },
    {
      "id": 4,
      "group": "PFA",
      "surface": "LA ENDO (CT).vtk",
      "comment": "",
      "x": -5.791499245984198,
      "y": -179.2988696059046,
      "z": -137.62842096253283
    },
    {
      "id": 5,
      "group": "PFA",
      "surface": "LA ENDO (CT).vtk",
      "comment": "",
      "x": -3.6354889182418333,
      "y": -180.71077036214922,
      "z": -143.42054759378576
    },
    {
      "id": 6,
      "group": "PFA",
      "surface": "LA ENDO (CT).vtk",
      "comment": "",
      "x": -31.533473515952636,
      "y": -148.48908691179759,
      "z": -154.15926220231404
    },
    {
      "id": 7,
      "group": "PFA",
      "surface": "LA ENDO (CT).vtk",
      "comment": "",
      "x": -1.6798677175328578,
      "y": -155.36469975043005,
      "z": -151.61372794785078
    },
    {
      "id": 8,
      "group": "PFA",
      "surface": "LA ENDO (CT).vtk",
      "comment": "",
      "x": 0.33425943474568953,
      "y": -159.24782598433603,
      "z": -148.82257812762887
    },
    {
      "id": 9,
      "group": "PFA",
      "surface": "LA ENDO (CT).vtk",
      "comment": "",
      "x": -0.10922922677039537,
      "y": -163.24673233062362,
      "z": -146.67130289675887
    },
    {
      "id": 10,
      "group": "PFA",
      "surface": "LA ENDO (CT).vtk",
      "comment": "",
      "x": -0.5638471811797672,
      "y": -171.5628505502004,
      "z": -143.77313148620118
    },
    {
      "id": 11,
      "group": "PFA",
      "surface": "LA ENDO (CT).vtk",
      "comment": "",
      "x": -1.0571571888161202,
      "y": -174.29657701891486,
      "z": -143.1430139552396
    },
    {
      "id": 12,
      "group": "PFA",
      "surface": "LA ENDO (CT).vtk",
      "comment": "",
      "x": -0.7794796068718881,
      "y": -182.64293767256618,
      "z": -141.54681831104796
    },
    {
      "id": 13,
      "group": "PFA",
      "surface": "LA ENDO (CT).vtk",
      "comment": "",
      "x": -0.21540004063962215,
      "y": -185.84395060511798,
      "z": -140.84095292291946
    },
    {
      "id": 14,
      "group": "PFA",
      "surface": "LA ENDO (CT).vtk",
      "comment": "",
      "x": 4.984307274860839,
      "y": -191.12448849425513,
      "z": -138.4994154720616
    },
    {
      "id": 15,
      "group": "PFA",
      "surface": "LA ENDO (CT).vtk",
      "comment": "",
      "x": -20.06868682651148,
      "y": -186.39277310146943,
      "z": -133.8748429614454
    },
    {
      "id": 16,
      "group": "PFA",
      "surface": "LA ENDO (CT).vtk",
      "comment": "",
      "x": 10.229252915608551,
      "y": -190.94571884692326,
      "z": -136.24958453406896
    },
    {
      "id": 17,
      "group": "PFA",
      "surface": "LA ENDO (CT).vtk",
      "comment": "",
      "x": 16.588675189618726,
      "y": -189.19705507936519,
      "z": -132.8376819911777
    },
    {
      "id": 18,
      "group": "PFA",
      "surface": "LA ENDO (CT).vtk",
      "comment": "",
      "x": 18.972673897727393,
      "y": -185.45878714326,
      "z": -131.19035272904503
    },
    {
      "id": 19,
      "group": "PFA",
      "surface": "LA ENDO (CT).vtk",
      "comment": "",
      "x": 20.493841121863646,
      "y": -179.8833740759249,
      "z": -129.5455488624404
    },
    {
      "id": 20,
      "group": "PFA",
      "surface": "LA ENDO (CT).vtk",
      "comment": "",
      "x": 21.880968116729388,
      "y": -173.85193701029925,
      "z": -128.98394246506325
    },
    {
      "id": 21,
      "group": "PFA",
      "surface": "LA ENDO (CT).vtk",
      "comment": "",
      "x": 22.20830932782216,
      "y": -168.15913505926807,
      "z": -129.4260768650786
    },
    {
      "id": 22,
      "group": "PFA",
      "surface": "LA ENDO (CT).vtk",
      "comment": "",
      "x": 22.617673174880863,
      "y": -160.13065963880805,
      "z": -130.90219739749296
    },
    {
      "id": 23,
      "group": "PFA",
      "surface": "LA ENDO (CT).vtk",
      "comment": "",
      "x": 21.88669885510911,
      "y": -155.19066154753241,
      "z": -132.58095994051433
    },
    {
      "id": 24,
      "group": "PFA",
      "surface": "LA ENDO (CT).vtk",
      "comment": "",
      "x": 21.58605560335198,
      "y": -148.9146710843428,
      "z": -135.89584446059095
    },
    {
      "id": 25,
      "group": "PFA",
      "surface": "LA ENDO (CT).vtk",
      "comment": "",
      "x": 20.80709127672967,
      "y": -143.46403487265422,
      "z": -140.40802632326398
    },
    {
      "id": 26,
      "group": "PFA",
      "surface": "LA ENDO (CT).vtk",
      "comment": "",
      "x": 18.24546261051063,
      "y": -142.01668406159126,
      "z": -148.13673424073636
    },
    {
      "id": 27,
      "group": "PFA",
      "surface": "LA ENDO (CT).vtk",
      "comment": "",
      "x": 16.229846839039084,
      "y": -145.12683118120293,
      "z": -152.03925608724762
    },
    {
      "id": 28,
      "group": "PFA",
      "surface": "LA ENDO (CT).vtk",
      "comment": "",
      "x": 13.206302557292986,
      "y": -149.1323912256921,
      "z": -150.62878327955536
    },
    {
      "id": 29,
      "group": "PFA",
      "surface": "LA ENDO (CT).vtk",
      "comment": "",
      "x": 9.706188239349729,
      "y": -151.92255338229785,
      "z": -150.6010791479223
    },
    {
      "id": 30,
      "group": "PFA",
      "surface": "LA ENDO (CT).vtk",
      "comment": "",
      "x": 7.573949471745777,
      "y": -154.24775587261774,
      "z": -149.58924190646286
    },
    {
      "id": 31,
      "group": "PFA",
      "surface": "LA ENDO (CT).vtk",
      "comment": "",
      "x": 5.2900519109354605,
      "y": -157.15236357306006,
      "z": -147.86669374666846
    },
    {
      "id": 32,
      "group": "PFA",
      "surface": "LA ENDO (CT).vtk",
      "comment": "",
      "x": 64.39483148936979,
      "y": -156.1929940860839,
      "z": -177.86410813988687
    },
    {
      "id": 33,
      "group": "PFA",
      "surface": "LA ENDO (CT).vtk",
      "comment": "",
      "x": 60.850369634537216,
      "y": -155.99125871536097,
      "z": -162.3797746789113
    },
    {
      "id": 34,
      "group": "PFA",
      "surface": "LA ENDO (CT).vtk",
      "comment": "",
      "x": 60.66067697505632,
      "y": -158.77426212084177,
      "z": -154.2958950690476
    },
    {
      "id": 35,
      "group": "PFA",
      "surface": "LA ENDO (CT).vtk",
      "comment": "",
      "x": 60.55302400924181,
      "y": -162.44192511193265,
      "z": -148.2793791392789
    },
    {
      "id": 36,
      "group": "PFA",
      "surface": "LA ENDO (CT).vtk",
      "comment": "",
      "x": 61.475816411754124,
      "y": -167.55264805942386,
      "z": -144.15138880828172
    },
    {
      "id": 37,
      "group": "PFA",
      "surface": "LA ENDO (CT).vtk",
      "comment": "",
      "x": 61.55493406841855,
      "y": -176.78845797462952,
      "z": -140.55032851472325
    },
    {
      "id": 38,
      "group": "PFA",
      "surface": "LA ENDO (CT).vtk",
      "comment": "",
      "x": 60.5594568718562,
      "y": -188.39263747088532,
      "z": -144.39576967250585
    },
    {
      "id": 39,
      "group": "PFA",
      "surface": "LA ENDO (CT).vtk",
      "comment": "",
      "x": 62.77161247535663,
      "y": -192.24710162208862,
      "z": -148.1495384063958
    },
    {
      "id": 40,
      "group": "PFA",
      "surface": "LA ENDO (CT).vtk",
      "comment": "",
      "x": 67.62504171520989,
      "y": -195.8450279384522,
      "z": -158.7603660923947
    },
    {
      "id": 41,
      "group": "PFA",
      "surface": "LA ENDO (CT).vtk",
      "comment": "",
      "x": 70.07990538548303,
      "y": -195.2160150488764,
      "z": -166.62709128434474
    },
    {
      "id": 42,
      "group": "PFA",
      "surface": "LA ENDO (CT).vtk",
      "comment": "",
      "x": 72.1423186903854,
      "y": -192.13458003285464,
      "z": -173.93753649642042
    },
    {
      "id": 43,
      "group": "PFA",
      "surface": "LA ENDO (CT).vtk",
      "comment": "",
      "x": 73.30558894232634,
      "y": -185.00610095014616,
      "z": -183.19886895259657
    },
    {
      "id": 44,
      "group": "PFA",
      "surface": "LA ENDO (CT).vtk",
      "comment": "",
      "x": 64.11172074954203,
      "y": -159.01228553394077,
      "z": -186.68302280232936
    },
    {
      "id": 45,
      "group": "PFA",
      "surface": "LA ENDO (CT).vtk",
      "comment": "",
      "x": 66.28905448878118,
      "y": -162.69539045416496,
      "z": -189.82733712352112
    },
    {
      "id": 46,
      "group": "PFA",
      "surface": "LA ENDO (CT).vtk",
      "comment": "",
      "x": 68.30212703396487,
      "y": -168.2449150433907,
      "z": -190.92353021664536
    },
    {
      "id": 47,
      "group": "PFA",
      "surface": "LA ENDO (CT).vtk",
      "comment": "",
      "x": 69.8054806571048,
      "y": -173.7179949657573,
      "z": -190.69522255996847
    },
    {
      "id": 48,
      "group": "PFA",
      "surface": "LA ENDO (CT).vtk",
      "comment": "",
      "x": 72.39190570953969,
      "y": -180.31698567535994,
      "z": -187.68287238675904
    },
    {
      "id": 49,
      "group": "PFA",
      "surface": "LA ENDO (CT).vtk",
      "comment": "",
      "x": 24.778401945413357,
      "y": -153.58514924383252,
      "z": -133.1776485252236
    },
    {
      "id": 50,
      "group": "PFA",
      "surface": "LA ENDO (CT).vtk",
      "comment": "",
      "x": 32.234892355184876,
      "y": -153.98247184194804,
      "z": -133.6923549911649
    },
    {
      "id": 51,
      "group": "PFA",
      "surface": "LA ENDO (CT).vtk",
      "comment": "",
      "x": 34.566861945470066,
      "y": -154.71682838760154,
      "z": -134.07582375079596
    },
    {
      "id": 52,
      "group": "PFA",
      "surface": "LA ENDO (CT).vtk",
      "comment": "",
      "x": 39.7930892936725,
      "y": -155.9584227055437,
      "z": -136.11875969001716
    },
    {
      "id": 53,
      "group": "PFA",
      "surface": "LA ENDO (CT).vtk",
      "comment": "",
      "x": 46.1450732446851,
      "y": -158.15124594985045,
      "z": -140.28790367811442
    },
    {
      "id": 54,
      "group": "PFA",
      "surface": "LA ENDO (CT).vtk",
      "comment": "",
      "x": 51.76139498110919,
      "y": -160.52389440499843,
      "z": -144.98209280717214
    },
    {
      "id": 55,
      "group": "PFA",
      "surface": "LA ENDO (CT).vtk",
      "comment": "",
      "x": 56.74401421373583,
      "y": -161.85171156695984,
      "z": -147.35407421030357
    },
    {
      "id": 56,
      "group": "PFA",
      "surface": "LA ENDO (CT).vtk",
      "comment": "",
      "x": 25.74328309631288,
      "y": -172.00322325308076,
      "z": -128.9250450271116
    },
    {
      "id": 57,
      "group": "PFA",
      "surface": "LA ENDO (CT).vtk",
      "comment": "",
      "x": 31.318959611310916,
      "y": -172.24565104505047,
      "z": -129.59877901116315
    },
    {
      "id": 58,
      "group": "PFA",
      "surface": "LA ENDO (CT).vtk",
      "comment": "",
      "x": 35.29230378133102,
      "y": -172.41825611796907,
      "z": -130.5435852757185
    },
    {
      "id": 59,
      "group": "PFA",
      "surface": "LA ENDO (CT).vtk",
      "comment": "",
      "x": 38.28959131941632,
      "y": -173.37394689669057,
      "z": -131.46776620855422
    },
    {
      "id": 60,
      "group": "PFA",
      "surface": "LA ENDO (CT).vtk",
      "comment": "",
      "x": 41.878878887735205,
      "y": -174.3030335727061,
      "z": -133.19568981755143
    },
    {
      "id": 61,
      "group": "PFA",
      "surface": "LA ENDO (CT).vtk",
      "comment": "",
      "x": 45.766515879932236,
      "y": -175.25356591170203,
      "z": -135.27030371323454
    },
    {
      "id": 62,
      "group": "PFA",
      "surface": "LA ENDO (CT).vtk",
      "comment": "",
      "x": 50.55822135153425,
      "y": -177.07809703149178,
      "z": -138.1055307556572
    },
    {
      "id": 63,
      "group": "PFA",
      "surface": "LA ENDO (CT).vtk",
      "comment": "",
      "x": 55.56530165076748,
      "y": -178.59740549983468,
      "z": -140.30758701855308
    },
    {
      "id": 64,
      "group": "PFA",
      "surface": "LA ENDO (CT).vtk",
      "comment": "",
      "x": 60.12424920746875,
      "y": -178.78942733851557,
      "z": -140.64719652489148
    },
    {
      "id": 65,
      "group": "RF",
      "surface": "LA ENDO (CT).vtk",
      "comment": "",
      "x": 56.733399784242444,
      "y": -185.31495129479512,
      "z": -195.50881508742327
    },
    {
      "id": 66,
      "group": "RF",
      "surface": "LA ENDO (CT).vtk",
      "comment": "",
      "x": 53.15716503312202,
      "y": -188.2692345685763,
      "z": -195.33353866210737
    },
    {
      "id": 67,
      "group": "RF",
      "surface": "LA ENDO (CT).vtk",
      "comment": "",
      "x": 49.6594815475902,
      "y": -190.52852116377434,
      "z": -194.86433789496402
    },
    {
      "id": 68,
      "group": "RF",
      "surface": "LA ENDO (CT).vtk",
      "comment": "",
      "x": 44.67427214477717,
      "y": -193.0165838276873,
      "z": -194.5481721222755
    },
    {
      "id": 69,
      "group": "RF",
      "surface": "LA ENDO (CT).vtk",
      "comment": "",
      "x": 40.758936737250366,
      "y": -194.3101728430491,
      "z": -193.94867321963443
    },
    {
      "id": 70,
      "group": "RF",
      "surface": "LA ENDO (CT).vtk",
      "comment": "",
      "x": 37.4027903948827,
      "y": -195.737647208634,
      "z": -193.128531086904
    },
    {
      "id": 71,
      "group": "RF",
      "surface": "LA ENDO (CT).vtk",
      "comment": "",
      "x": 32.77339270823474,
      "y": -197.54691851504506,
      "z": -192.8004639320669
    },
    {
      "id": 72,
      "group": "RF",
      "surface": "LA ENDO (CT).vtk",
      "comment": "",
      "x": 28.328595404377367,
      "y": -198.79564946842402,
      "z": -191.58306524566905
    },
    {
      "id": 73,
      "group": "RF",
      "surface": "LA ENDO (CT).vtk",
      "comment": "",
      "x": 20.331861462776374,
      "y": -201.3479805504577,
      "z": -191.80403499278208
    },
    {
      "id": 74,
      "group": "RF",
      "surface": "LA ENDO (CT).vtk",
      "comment": "",
      "x": 18.052118625246536,
      "y": -202.32700563113602,
      "z": -191.9496997757982
    },
    {
      "id": 75,
      "group": "RF",
      "surface": "LA ENDO (CT).vtk",
      "comment": "",
      "x": 24.922717795492403,
      "y": -200.19772084954135,
      "z": -191.1321010356697
    },
    {
      "id": 76,
      "group": "PFA",
      "surface": "LA ENDO (CT).vtk",
      "comment": "",
      "x": 66.79159299675055,
      "y": -176.1030637480591,
      "z": -193.05444745710219
    },
    {
      "id": 77,
      "group": "PFA",
      "surface": "LA ENDO (CT).vtk",
      "comment": "",
      "x": 63.52465325019998,
      "y": -180.15519601825773,
      "z": -194.7910389884645
    },
    {
      "id": 78,
      "group": "PFA",
      "surface": "LA ENDO (CT).vtk",
      "comment": "",
      "x": 62.16456925733439,
      "y": -182.31225632672619,
      "z": -194.8730564554162
    },
    {
      "id": 79,
      "group": "RF",
      "surface": "LA ENDO (CT).vtk",
      "comment": "",
      "x": -12.67120222251171,
      "y": -192.42284404291718,
      "z": -164.2795754005382
    },
    {
      "id": 80,
      "group": "RF",
      "surface": "LA ENDO (CT).vtk",
      "comment": "",
      "x": -13.322787150892736,
      "y": -191.76211785894762,
      "z": -159.9588151440862
    },
    {
      "id": 81,
      "group": "PFA",
      "surface": "LA ENDO (CT).vtk",
      "comment": "",
      "x": -11.176475362431006,
      "y": -190.5303224303766,
      "z": -150.3143731727439
    },
    {
      "id": 82,
      "group": "PFA",
      "surface": "LA ENDO (CT).vtk",
      "comment": "",
      "x": -12.479895765885544,
      "y": -192.9120922820087,
      "z": -153.32511382908055
    },
    {
      "id": 83,
      "group": "PFA",
      "surface": "RA ENDO (CT).vtk",
      "comment": "",
      "x": 60.6149639271282,
      "y": -159.70134828376516,
      "z": -211.71544152371
    },
    {
      "id": 84,
      "group": "PFA",
      "surface": "RA ENDO (CT).vtk",
      "comment": "",
      "x": 65.11011149800743,
      "y": -163.28394922661573,
      "z": -209.4142733881559
    },
    {
      "id": 85,
      "group": "PFA",
      "surface": "RA ENDO (CT).vtk",
      "comment": "",
      "x": 67.48786439323499,
      "y": -166.277956011007,
      "z": -204.39350315063834
    },
    {
      "id": 86,
      "group": "PFA",
      "surface": "RA ENDO (CT).vtk",
      "comment": "",
      "x": 67.002562504505,
      "y": -167.1883439677778,
      "z": -199.24002577765435
    },
    {
      "id": 87,
      "group": "PFA",
      "surface": "RA ENDO (CT).vtk",
      "comment": "",
      "x": 59.73641171155364,
      "y": -151.09461599324007,
      "z": -211.46628053367317
    },
    {
      "id": 88,
      "group": "PFA",
      "surface": "RA ENDO (CT).vtk",
      "comment": "",
      "x": 52.053022228979614,
      "y": -154.1536008720783,
      "z": -209.31637569262037
    },
    {
      "id": 89,
      "group": "PFA",
      "surface": "RA ENDO (CT).vtk",
      "comment": "",
      "x": 49.174267207291564,
      "y": -152.24685481027907,
      "z": -205.40801807160952
    },
    {
      "id": 90,
      "group": "PFA",
      "surface": "RA ENDO (CT).vtk",
      "comment": "",
      "x": 22.373935457061776,
      "y": -197.0636676122664,
      "z": -197.75291909433463
    },
    {
      "id": 91,
      "group": "PFA",
      "surface": "RA ENDO (CT).vtk",
      "comment": "",
      "x": 47.973507131161114,
      "y": -152.8232482965142,
      "z": -201.37280174328524
    },
    {
      "id": 92,
      "group": "PFA",
      "surface": "RA ENDO (CT).vtk",
      "comment": "",
      "x": 49.69542111638523,
      "y": -153.81856023501348,
      "z": -196.62186002887196
    },
    {
      "id": 93,
      "group": "PFA",
      "surface": "RA ENDO (CT).vtk",
      "comment": "",
      "x": 53.37862455502153,
      "y": -153.73582763339857,
      "z": -193.4434784327628
    },
    {
      "id": 94,
      "group": "PFA",
      "surface": "RA ENDO (CT).vtk",
      "comment": "",
      "x": 58.74416705175129,
      "y": -153.7415458992341,
      "z": -190.90136866040234
    },
    {
      "id": 95,
      "group": "PFA",
      "surface": "RA ENDO (CT).vtk",
      "comment": "",
      "x": 63.38913381418881,
      "y": -152.7164129347542,
      "z": -189.77242648639145
    },
    {
      "id": 96,
      "group": "PFA",
      "surface": "RA ENDO (CT).vtk",
      "comment": "",
      "x": 65.50055768930282,
      "y": -163.84883566652692,
      "z": -196.06193089703083
    },
    {
      "id": 97,
      "group": "PFA",
      "surface": "RA ENDO (CT).vtk",
      "comment": "",
      "x": 66.79742681345212,
      "y": -169.98578132178534,
      "z": -205.94479617992454
    },
    {
      "id": 98,
      "group": "PFA",
      "surface": "RA ENDO (CT).vtk",
      "comment": "",
      "x": 64.55791188130132,
      "y": -178.47272565063912,
      "z": -206.59316775509632
    },
    {
      "id": 99,
      "group": "PFA",
      "surface": "RA ENDO (CT).vtk",
      "comment": "",
      "x": 63.11083009172586,
      "y": -184.88917285302887,
      "z": -205.55214304196744
    },
    {
      "id": 100,
      "group": "PFA",
      "surface": "RA ENDO (CT).vtk",
      "comment": "",
      "x": 63.553360078745726,
      "y": -191.4586976434257,
      "z": -203.74004715164835
    },
    {
      "id": 101,
      "group": "PFA",
      "surface": "RA ENDO (CT).vtk",
      "comment": "",
      "x": 65.16028807273858,
      "y": -198.15239591892805,
      "z": -202.31960022777733
    },
    {
      "id": 102,
      "group": "PFA",
      "surface": "RA ENDO (CT).vtk",
      "comment": "",
      "x": 65.00484671805864,
      "y": -206.4785474011279,
      "z": -196.49274271650154
    },
    {
      "id": 103,
      "group": "PFA",
      "surface": "RA ENDO (CT).vtk",
      "comment": "",
      "x": 65.80737477829359,
      "y": -209.21407729610166,
      "z": -194.9211727752117
    },
    {
      "id": 104,
      "group": "PFA",
      "surface": "RA ENDO (CT).vtk",
      "comment": "",
      "x": 65.98941590876149,
      "y": -215.15379634219605,
      "z": -192.59465744189887
    },
    {
      "id": 105,
      "group": "PFA",
      "surface": "RA ENDO (CT).vtk",
      "comment": "",
      "x": 65.61322295246052,
      "y": -219.0760393186744,
      "z": -190.586043391092
    },
    {
      "id": 106,
      "group": "PFA",
      "surface": "RA ENDO (CT).vtk",
      "comment": "",
      "x": 66.01026267117962,
      "y": -222.59243590728832,
      "z": -189.86475502400566
    },
    {
      "id": 107,
      "group": "PFA",
      "surface": "RA ENDO (CT).vtk",
      "comment": "",
      "x": 66.82413503984333,
      "y": -226.8512885674335,
      "z": -189.14843393103078
    },
    {
      "id": 108,
      "group": "PFA",
      "surface": "RA ENDO (CT).vtk",
      "comment": "",
      "x": 64.82705792493527,
      "y": -202.59010320463068,
      "z": -199.76255890953635
    },
    {
      "id": 109,
      "group": "PFA",
      "surface": "RA ENDO (CT).vtk",
      "comment": "",
      "x": 65.70533267795702,
      "y": -174.92527743441656,
      "z": -206.7361521529715
    },
    {
      "id": 110,
      "group": "RF",
      "surface": "RA ENDO (CT).vtk",
      "comment": "",
      "x": 21.656881704388596,
      "y": -223.7400580061198,
      "z": -219.60838447386246
    },
    {
      "id": 111,
      "group": "RF",
      "surface": "RA ENDO (CT).vtk",
      "comment": "",
      "x": 25.26183097118623,
      "y": -230.84846889710022,
      "z": -218.1926598218091
    },
    {
      "id": 112,
      "group": "RF",
      "surface": "RA ENDO (CT).vtk",
      "comment": "",
      "x": 26.67187738848134,
      "y": -233.1454708214186,
      "z": -216.4824567409227
    },
    {
      "id": 113,
      "group": "RF",
      "surface": "RA ENDO (CT).vtk",
      "comment": "",
      "x": 29.06500824626091,
      "y": -235.35893809045754,
      "z": -213.71463845756875
    },
    {
      "id": 114,
      "group": "RF",
      "surface": "RA ENDO (CT).vtk",
      "comment": "",
      "x": 32.64128420130273,
      "y": -235.27398163601924,
      "z": -210.75278569198997
    },
    {
      "id": 115,
      "group": "RF",
      "surface": "RA ENDO (CT).vtk",
      "comment": "",
      "x": 35.07633455832299,
      "y": -234.40180923155833,
      "z": -208.37161410605702
    },
    {
      "id": 116,
      "group": "RF",
      "surface": "RA ENDO (CT).vtk",
      "comment": "",
      "x": 38.79793752588717,
      "y": -237.43898646349808,
      "z": -204.86428195697778
    },
    {
      "id": 117,
      "group": "RF",
      "surface": "RA ENDO (CT).vtk",
      "comment": "",
      "x": 40.9987426757898,
      "y": -237.55368171978247,
      "z": -202.78074557774087
    }
  ]
}